README.rst
setup.py
sageone/__init__.py
sageone/client.py
sageone_api_client.egg-info/PKG-INFO
sageone_api_client.egg-info/SOURCES.txt
sageone_api_client.egg-info/dependency_links.txt
sageone_api_client.egg-info/not-zip-safe
sageone_api_client.egg-info/requires.txt
sageone_api_client.egg-info/top_level.txt