Metadata-Version: 1.1
Name: sageone-api-client
Version: 0.0.2
Summary: Sage One API Client
Home-page: https://github.com/maxnaude/sageone-api-client
Author: Max Naude
Author-email: maxnaude@gmail.com
License: UNKNOWN
Platform: UNKNOWN
Classifier: Development Status :: 4 - Beta
Classifier: Intended Audience :: Developers
Classifier: License :: OSI Approved :: BSD License
Classifier: Operating System :: POSIX
Classifier: Programming Language :: Python
Classifier: Topic :: Software Development :: Libraries :: Python Modules
Classifier: Topic :: System :: Networking
